{
	"start":	{
		"connected":	[{
				"socket":	5,
				"local_host":	"192.168.1.243",
				"local_port":	40336,
				"remote_host":	"192.168.1.165",
				"remote_port":	5201
			}],
		"version":	"iperf 3.19.1",
		"system_info":	"Linux blind-warrior 6.12.47 #1-NixOS SMP PREEMPT_DYNAMIC Thu Sep 11 15:21:47 UTC 2025 x86_64",
		"timestamp":	{
			"time":	"Thu, 27 Nov 2025 22:50:21 GMT",
			"timesecs":	1764283821
		},
		"connecting_to":	{
			"host":	"192.168.1.165",
			"port":	5201
		},
		"cookie":	"spao2vbh6n336e2xurxo5dx6cmhzpzmhz2y5",
		"tcp_mss_default":	1448,
		"target_bitrate":	0,
		"fq_rate":	0,
		"sock_bufsize":	0,
		"sndbuf_actual":	16384,
		"rcvbuf_actual":	131072,
		"test_start":	{
			"protocol":	"TCP",
			"num_streams":	1,
			"blksize":	131072,
			"omit":	0,
			"duration":	30,
			"bytes":	0,
			"blocks":	0,
			"reverse":	0,
			"tos":	0,
			"target_bitrate":	0,
			"bidir":	0,
			"fqrate":	0,
			"interval":	1
		}
	},
	"intervals":	[{
			"streams":	[{
					"socket":	5,
					"start":	0,
					"end":	1.000156,
					"seconds":	1.000156044960022,
					"bytes":	2752512,
					"bits_per_second":	22016660.411106333,
					"retransmits":	0,
					"snd_cwnd":	108600,
					"snd_wnd":	209408,
					"rtt":	23675,
					"rttvar":	4111,
					"pmtu":	1500,
					"omitted":	false,
					"sender":	true
				}],
			"sum":	{
				"start":	0,
				"end":	1.000156,
				"seconds":	1.000156044960022,
				"bytes":	2752512,
				"bits_per_second":	22016660.411106333,
				"retransmits":	0,
				"omitted":	false,
				"sender":	true
			}
		}, {
			"streams":	[{
					"socket":	5,
					"start":	1.000156,
					"end":	2.000157,
					"seconds":	1.0000009536743164,
					"bytes":	2490368,
					"bits_per_second":	19922925.00001812,
					"retransmits":	0,
					"snd_cwnd":	108600,
					"snd_wnd":	209408,
					"rtt":	23895,
					"rttvar":	4671,
					"pmtu":	1500,
					"omitted":	false,
					"sender":	true
				}],
			"sum":	{
				"start":	1.000156,
				"end":	2.000157,
				"seconds":	1.0000009536743164,
				"bytes":	2490368,
				"bits_per_second":	19922925.00001812,
				"retransmits":	0,
				"omitted":	false,
				"sender":	true
			}
		}, {
			"streams":	[{
					"socket":	5,
					"start":	2.000157,
					"end":	3.000156,
					"seconds":	0.99999898672103882,
					"bytes":	2228224,
					"bits_per_second":	17825810.0625183,
					"retransmits":	0,
					"snd_cwnd":	108600,
					"snd_wnd":	209408,
					"rtt":	24543,
					"rttvar":	4112,
					"pmtu":	1500,
					"omitted":	false,
					"sender":	true
				}],
			"sum":	{
				"start":	2.000157,
				"end":	3.000156,
				"seconds":	0.99999898672103882,
				"bytes":	2228224,
				"bits_per_second":	17825810.0625183,
				"retransmits":	0,
				"omitted":	false,
				"sender":	true
			}
		}, {
			"streams":	[{
					"socket":	5,
					"start":	3.000156,
					"end":	4.000157,
					"seconds":	1.0000009536743164,
					"bytes":	2490368,
					"bits_per_second":	19922925.00001812,
					"retransmits":	0,
					"snd_cwnd":	108600,
					"snd_wnd":	209408,
					"rtt":	22779,
					"rttvar":	4193,
					"pmtu":	1500,
					"omitted":	false,
					"sender":	true
				}],
			"sum":	{
				"start":	3.000156,
				"end":	4.000157,
				"seconds":	1.0000009536743164,
				"bytes":	2490368,
				"bits_per_second":	19922925.00001812,
				"retransmits":	0,
				"omitted":	false,
				"sender":	true
			}
		}, {
			"streams":	[{
					"socket":	5,
					"start":	4.000157,
					"end":	5.000157,
					"seconds":	1,
					"bytes":	2228224,
					"bits_per_second":	17825792,
					"retransmits":	0,
					"snd_cwnd":	108600,
					"snd_wnd":	209408,
					"rtt":	22295,
					"rttvar":	3626,
					"pmtu":	1500,
					"omitted":	false,
					"sender":	true
				}],
			"sum":	{
				"start":	4.000157,
				"end":	5.000157,
				"seconds":	1,
				"bytes":	2228224,
				"bits_per_second":	17825792,
				"retransmits":	0,
				"omitted":	false,
				"sender":	true
			}
		}, {
			"streams":	[{
					"socket":	5,
					"start":	5.000157,
					"end":	6.000215,
					"seconds":	1.0000580549240112,
					"bytes":	2490368,
					"bits_per_second":	19921787.44214388,
					"retransmits":	0,
					"snd_cwnd":	108600,
					"snd_wnd":	209408,
					"rtt":	24134,
					"rttvar":	3513,
					"pmtu":	1500,
					"omitted":	false,
					"sender":	true
				}],
			"sum":	{
				"start":	5.000157,
				"end":	6.000215,
				"seconds":	1.0000580549240112,
				"bytes":	2490368,
				"bits_per_second":	19921787.44214388,
				"retransmits":	0,
				"omitted":	false,
				"sender":	true
			}
		}, {
			"streams":	[{
					"socket":	5,
					"start":	6.000215,
					"end":	7.000159,
					"seconds":	0.999943971633911,
					"bytes":	2490368,
					"bits_per_second":	19924060.312545169,
					"retransmits":	0,
					"snd_cwnd":	108600,
					"snd_wnd":	209408,
					"rtt":	23845,
					"rttvar":	4716,
					"pmtu":	1500,
					"omitted":	false,
					"sender":	true
				}],
			"sum":	{
				"start":	6.000215,
				"end":	7.000159,
				"seconds":	0.999943971633911,
				"bytes":	2490368,
				"bits_per_second":	19924060.312545169,
				"retransmits":	0,
				"omitted":	false,
				"sender":	true
			}
		}, {
			"streams":	[{
					"socket":	5,
					"start":	7.000159,
					"end":	8.000168,
					"seconds":	1.0000089406967163,
					"bytes":	2359296,
					"bits_per_second":	18874199.251508728,
					"retransmits":	0,
					"snd_cwnd":	149144,
					"snd_wnd":	209408,
					"rtt":	24986,
					"rttvar":	2442,
					"pmtu":	1500,
					"omitted":	false,
					"sender":	true
				}],
			"sum":	{
				"start":	7.000159,
				"end":	8.000168,
				"seconds":	1.0000089406967163,
				"bytes":	2359296,
				"bits_per_second":	18874199.251508728,
				"retransmits":	0,
				"omitted":	false,
				"sender":	true
			}
		}, {
			"streams":	[{
					"socket":	5,
					"start":	8.000168,
					"end":	9.000162,
					"seconds":	0.99999397993087769,
					"bytes":	2490368,
					"bits_per_second":	19923063.938222036,
					"retransmits":	0,
					"snd_cwnd":	149144,
					"snd_wnd":	209408,
					"rtt":	24814,
					"rttvar":	3202,
					"pmtu":	1500,
					"omitted":	false,
					"sender":	true
				}],
			"sum":	{
				"start":	8.000168,
				"end":	9.000162,
				"seconds":	0.99999397993087769,
				"bytes":	2490368,
				"bits_per_second":	19923063.938222036,
				"retransmits":	0,
				"omitted":	false,
				"sender":	true
			}
		}, {
			"streams":	[{
					"socket":	5,
					"start":	9.000162,
					"end":	10.000162,
					"seconds":	1,
					"bytes":	2490368,
					"bits_per_second":	19922944,
					"retransmits":	0,
					"snd_cwnd":	149144,
					"snd_wnd":	209408,
					"rtt":	25567,
					"rttvar":	2369,
					"pmtu":	1500,
					"omitted":	false,
					"sender":	true
				}],
			"sum":	{
				"start":	9.000162,
				"end":	10.000162,
				"seconds":	1,
				"bytes":	2490368,
				"bits_per_second":	19922944,
				"retransmits":	0,
				"omitted":	false,
				"sender":	true
			}
		}, {
			"streams":	[{
					"socket":	5,
					"start":	10.000162,
					"end":	11.000217,
					"seconds":	1.0000549554824829,
					"bytes":	2228224,
					"bits_per_second":	17824812.428832807,
					"retransmits":	0,
					"snd_cwnd":	149144,
					"snd_wnd":	209408,
					"rtt":	25329,
					"rttvar":	4453,
					"pmtu":	1500,
					"omitted":	false,
					"sender":	true
				}],
			"sum":	{
				"start":	10.000162,
				"end":	11.000217,
				"seconds":	1.0000549554824829,
				"bytes":	2228224,
				"bits_per_second":	17824812.428832807,
				"retransmits":	0,
				"omitted":	false,
				"sender":	true
			}
		}, {
			"streams":	[{
					"socket":	5,
					"start":	11.000217,
					"end":	12.000161,
					"seconds":	0.999943971633911,
					"bytes":	2490368,
					"bits_per_second":	19924060.312545169,
					"retransmits":	0,
					"snd_cwnd":	149144,
					"snd_wnd":	209408,
					"rtt":	23268,
					"rttvar":	2298,
					"pmtu":	1500,
					"omitted":	false,
					"sender":	true
				}],
			"sum":	{
				"start":	11.000217,
				"end":	12.000161,
				"seconds":	0.999943971633911,
				"bytes":	2490368,
				"bits_per_second":	19924060.312545169,
				"retransmits":	0,
				"omitted":	false,
				"sender":	true
			}
		}, {
			"streams":	[{
					"socket":	5,
					"start":	12.000161,
					"end":	13.000226,
					"seconds":	1.0000649690628052,
					"bytes":	2490368,
					"bits_per_second":	19921649.709088866,
					"retransmits":	0,
					"snd_cwnd":	149144,
					"snd_wnd":	209408,
					"rtt":	24804,
					"rttvar":	4307,
					"pmtu":	1500,
					"omitted":	false,
					"sender":	true
				}],
			"sum":	{
				"start":	12.000161,
				"end":	13.000226,
				"seconds":	1.0000649690628052,
				"bytes":	2490368,
				"bits_per_second":	19921649.709088866,
				"retransmits":	0,
				"omitted":	false,
				"sender":	true
			}
		}, {
			"streams":	[{
					"socket":	5,
					"start":	13.000226,
					"end":	14.000198,
					"seconds":	0.99997198581695557,
					"bytes":	2228224,
					"bits_per_second":	17826291.388989974,
					"retransmits":	0,
					"snd_cwnd":	149144,
					"snd_wnd":	209408,
					"rtt":	24114,
					"rttvar":	4681,
					"pmtu":	1500,
					"omitted":	false,
					"sender":	true
				}],
			"sum":	{
				"start":	13.000226,
				"end":	14.000198,
				"seconds":	0.99997198581695557,
				"bytes":	2228224,
				"bits_per_second":	17826291.388989974,
				"retransmits":	0,
				"omitted":	false,
				"sender":	true
			}
		}, {
			"streams":	[{
					"socket":	5,
					"start":	14.000198,
					"end":	15.000156,
					"seconds":	0.99995797872543335,
					"bytes":	2490368,
					"bits_per_second":	19923781.222681165,
					"retransmits":	0,
					"snd_cwnd":	149144,
					"snd_wnd":	209408,
					"rtt":	25212,
					"rttvar":	3320,
					"pmtu":	1500,
					"omitted":	false,
					"sender":	true
				}],
			"sum":	{
				"start":	14.000198,
				"end":	15.000156,
				"seconds":	0.99995797872543335,
				"bytes":	2490368,
				"bits_per_second":	19923781.222681165,
				"retransmits":	0,
				"omitted":	false,
				"sender":	true
			}
		}, {
			"streams":	[{
					"socket":	5,
					"start":	15.000156,
					"end":	16.000198,
					"seconds":	1.0000419616699219,
					"bytes":	2490368,
					"bits_per_second":	19922108.035078485,
					"retransmits":	0,
					"snd_cwnd":	149144,
					"snd_wnd":	209408,
					"rtt":	25713,
					"rttvar":	3983,
					"pmtu":	1500,
					"omitted":	false,
					"sender":	true
				}],
			"sum":	{
				"start":	15.000156,
				"end":	16.000198,
				"seconds":	1.0000419616699219,
				"bytes":	2490368,
				"bits_per_second":	19922108.035078485,
				"retransmits":	0,
				"omitted":	false,
				"sender":	true
			}
		}, {
			"streams":	[{
					"socket":	5,
					"start":	16.000198,
					"end":	17.000197,
					"seconds":	0.99999898672103882,
					"bytes":	2097152,
					"bits_per_second":	16777233.000017226,
					"retransmits":	0,
					"snd_cwnd":	149144,
					"snd_wnd":	209408,
					"rtt":	22950,
					"rttvar":	2682,
					"pmtu":	1500,
					"omitted":	false,
					"sender":	true
				}],
			"sum":	{
				"start":	16.000198,
				"end":	17.000197,
				"seconds":	0.99999898672103882,
				"bytes":	2097152,
				"bits_per_second":	16777233.000017226,
				"retransmits":	0,
				"omitted":	false,
				"sender":	true
			}
		}, {
			"streams":	[{
					"socket":	5,
					"start":	17.000197,
					"end":	18.000206,
					"seconds":	1.0000089406967163,
					"bytes":	2490368,
					"bits_per_second":	19922765.876592547,
					"retransmits":	0,
					"snd_cwnd":	149144,
					"snd_wnd":	209408,
					"rtt":	24838,
					"rttvar":	2842,
					"pmtu":	1500,
					"omitted":	false,
					"sender":	true
				}],
			"sum":	{
				"start":	17.000197,
				"end":	18.000206,
				"seconds":	1.0000089406967163,
				"bytes":	2490368,
				"bits_per_second":	19922765.876592547,
				"retransmits":	0,
				"omitted":	false,
				"sender":	true
			}
		}, {
			"streams":	[{
					"socket":	5,
					"start":	18.000206,
					"end":	19.000217,
					"seconds":	1.0000109672546387,
					"bytes":	2490368,
					"bits_per_second":	19922725.502396319,
					"retransmits":	0,
					"snd_cwnd":	149144,
					"snd_wnd":	209408,
					"rtt":	25033,
					"rttvar":	4417,
					"pmtu":	1500,
					"omitted":	false,
					"sender":	true
				}],
			"sum":	{
				"start":	18.000206,
				"end":	19.000217,
				"seconds":	1.0000109672546387,
				"bytes":	2490368,
				"bits_per_second":	19922725.502396319,
				"retransmits":	0,
				"omitted":	false,
				"sender":	true
			}
		}, {
			"streams":	[{
					"socket":	5,
					"start":	19.000217,
					"end":	20.000232,
					"seconds":	1.0000150203704834,
					"bytes":	2228224,
					"bits_per_second":	17825524.254021645,
					"retransmits":	0,
					"snd_cwnd":	149144,
					"snd_wnd":	209408,
					"rtt":	22657,
					"rttvar":	2974,
					"pmtu":	1500,
					"omitted":	false,
					"sender":	true
				}],
			"sum":	{
				"start":	19.000217,
				"end":	20.000232,
				"seconds":	1.0000150203704834,
				"bytes":	2228224,
				"bits_per_second":	17825524.254021645,
				"retransmits":	0,
				"omitted":	false,
				"sender":	true
			}
		}, {
			"streams":	[{
					"socket":	5,
					"start":	20.000232,
					"end":	21.000216,
					"seconds":	0.9999840259552002,
					"bytes":	2490368,
					"bits_per_second":	19923262.255083822,
					"retransmits":	0,
					"snd_cwnd":	149144,
					"snd_wnd":	209408,
					"rtt":	25625,
					"rttvar":	4073,
					"pmtu":	1500,
					"omitted":	false,
					"sender":	true
				}],
			"sum":	{
				"start":	20.000232,
				"end":	21.000216,
				"seconds":	0.9999840259552002,
				"bytes":	2490368,
				"bits_per_second":	19923262.255083822,
				"retransmits":	0,
				"omitted":	false,
				"sender":	true
			}
		}, {
			"streams":	[{
					"socket":	5,
					"start":	21.000216,
					"end":	22.000234,
					"seconds":	1.0000180006027222,
					"bytes":	2490368,
					"bits_per_second":	19922585.381455351,
					"retransmits":	0,
					"snd_cwnd":	149144,
					"snd_wnd":	209408,
					"rtt":	23406,
					"rttvar":	4373,
					"pmtu":	1500,
					"omitted":	false,
					"sender":	true
				}],
			"sum":	{
				"start":	21.000216,
				"end":	22.000234,
				"seconds":	1.0000180006027222,
				"bytes":	2490368,
				"bits_per_second":	19922585.381455351,
				"retransmits":	0,
				"omitted":	false,
				"sender":	true
			}
		}, {
			"streams":	[{
					"socket":	5,
					"start":	22.000234,
					"end":	23.000157,
					"seconds":	0.9999229907989502,
					"bytes":	2228224,
					"bits_per_second":	17827164.855722521,
					"retransmits":	0,
					"snd_cwnd":	149144,
					"snd_wnd":	209408,
					"rtt":	23986,
					"rttvar":	3106,
					"pmtu":	1500,
					"omitted":	false,
					"sender":	true
				}],
			"sum":	{
				"start":	22.000234,
				"end":	23.000157,
				"seconds":	0.9999229907989502,
				"bytes":	2228224,
				"bits_per_second":	17827164.855722521,
				"retransmits":	0,
				"omitted":	false,
				"sender":	true
			}
		}, {
			"streams":	[{
					"socket":	5,
					"start":	23.000157,
					"end":	24.00016,
					"seconds":	1.0000029802322388,
					"bytes":	2490368,
					"bits_per_second":	19922884.625176951,
					"retransmits":	0,
					"snd_cwnd":	149144,
					"snd_wnd":	209408,
					"rtt":	23743,
					"rttvar":	4641,
					"pmtu":	1500,
					"omitted":	false,
					"sender":	true
				}],
			"sum":	{
				"start":	23.000157,
				"end":	24.00016,
				"seconds":	1.0000029802322388,
				"bytes":	2490368,
				"bits_per_second":	19922884.625176951,
				"retransmits":	0,
				"omitted":	false,
				"sender":	true
			}
		}, {
			"streams":	[{
					"socket":	5,
					"start":	24.00016,
					"end":	25.001061,
					"seconds":	1.0009009838104248,
					"bytes":	2490368,
					"bits_per_second":	19905009.908326253,
					"retransmits":	0,
					"snd_cwnd":	149144,
					"snd_wnd":	209408,
					"rtt":	25113,
					"rttvar":	2177,
					"pmtu":	1500,
					"omitted":	false,
					"sender":	true
				}],
			"sum":	{
				"start":	24.00016,
				"end":	25.001061,
				"seconds":	1.0009009838104248,
				"bytes":	2490368,
				"bits_per_second":	19905009.908326253,
				"retransmits":	0,
				"omitted":	false,
				"sender":	true
			}
		}, {
			"streams":	[{
					"socket":	5,
					"start":	25.001061,
					"end":	26.00102,
					"seconds":	0.99995899200439453,
					"bytes":	2097152,
					"bits_per_second":	16777904.02821466,
					"retransmits":	0,
					"snd_cwnd":	149144,
					"snd_wnd":	209408,
					"rtt":	23791,
					"rttvar":	4293,
					"pmtu":	1500,
					"omitted":	false,
					"sender":	true
				}],
			"sum":	{
				"start":	25.001061,
				"end":	26.00102,
				"seconds":	0.99995899200439453,
				"bytes":	2097152,
				"bits_per_second":	16777904.02821466,
				"retransmits":	0,
				"omitted":	false,
				"sender":	true
			}
		}, {
			"streams":	[{
					"socket":	5,
					"start":	26.00102,
					"end":	27.000159,
					"seconds":	0.99913901090621948,
					"bytes":	2490368,
					"bits_per_second":	19940112.219149448,
					"retransmits":	0,
					"snd_cwnd":	149144,
					"snd_wnd":	209408,
					"rtt":	23562,
					"rttvar":	3161,
					"pmtu":	1500,
					"omitted":	false,
					"sender":	true
				}],
			"sum":	{
				"start":	26.00102,
				"end":	27.000159,
				"seconds":	0.99913901090621948,
				"bytes":	2490368,
				"bits_per_second":	19940112.219149448,
				"retransmits":	0,
				"omitted":	false,
				"sender":	true
			}
		}, {
			"streams":	[{
					"socket":	5,
					"start":	27.000159,
					"end":	28.000187,
					"seconds":	1.0000280141830444,
					"bytes":	2490368,
					"bits_per_second":	19922385.890634976,
					"retransmits":	0,
					"snd_cwnd":	149144,
					"snd_wnd":	209408,
					"rtt":	25001,
					"rttvar":	3326,
					"pmtu":	1500,
					"omitted":	false,
					"sender":	true
				}],
			"sum":	{
				"start":	27.000159,
				"end":	28.000187,
				"seconds":	1.0000280141830444,
				"bytes":	2490368,
				"bits_per_second":	19922385.890634976,
				"retransmits":	0,
				"omitted":	false,
				"sender":	true
			}
		}, {
			"streams":	[{
					"socket":	5,
					"start":	28.000187,
					"end":	29.000174,
					"seconds":	0.999987006187439,
					"bytes":	2228224,
					"bits_per_second":	17826023.628009729,
					"retransmits":	0,
					"snd_cwnd":	149144,
					"snd_wnd":	209408,
					"rtt":	23011,
					"rttvar":	4172,
					"pmtu":	1500,
					"omitted":	false,
					"sender":	true
				}],
			"sum":	{
				"start":	28.000187,
				"end":	29.000174,
				"seconds":	0.999987006187439,
				"bytes":	2228224,
				"bits_per_second":	17826023.628009729,
				"retransmits":	0,
				"omitted":	false,
				"sender":	true
			}
		}, {
			"streams":	[{
					"socket":	5,
					"start":	29.000174,
					"end":	30.000459,
					"seconds":	1.0002850294113159,
					"bytes":	2490368,
					"bits_per_second":	19917266.993113931,
					"retransmits":	0,
					"snd_cwnd":	149144,
					"snd_wnd":	209408,
					"rtt":	23652,
					"rttvar":	2207,
					"pmtu":	1500,
					"omitted":	false,
					"sender":	true
				}],
			"sum":	{
				"start":	29.000174,
				"end":	30.000459,
				"seconds":	1.0002850294113159,
				"bytes":	2490368,
				"bits_per_second":	19917266.993113931,
				"retransmits":	0,
				"omitted":	false,
				"sender":	true
			}
		}],
	"end":	{
		"streams":	[{
				"sender":	{
					"socket":	5,
					"start":	0,
					"end":	30.000459,
					"seconds":	30.000459,
					"bytes":	72220672,
					"bits_per_second":	19258551.21083314,
					"retransmits":	0,
					"max_snd_cwnd":	149144,
					"max_snd_wnd":	209408,
					"max_rtt":	25713,
					"min_rtt":	22295,
					"mean_rtt":	24178,
					"sender":	true
				},
				"receiver":	{
					"socket":	5,
					"start":	0,
					"end":	30.021328,
					"seconds":	30.000459,
					"bytes":	71565312,
					"bits_per_second":	19070525.327860247,
					"sender":	true
				}
			}],
		"sum_sent":	{
			"start":	0,
			"end":	30.000459,
			"seconds":	30.000459,
			"bytes":	72220672,
			"bits_per_second":	19258551.21083314,
			"retransmits":	0,
			"sender":	true
		},
		"sum_received":	{
			"start":	0,
			"end":	30.021328,
			"seconds":	30.021328,
			"bytes":	71565312,
			"bits_per_second":	19070525.327860247,
			"sender":	true
		},
		"cpu_utilization_percent":	{
			"host_total":	0.067807534714868251,
			"host_user":	0.0038226306064068558,
			"host_system":	0.0639882368291296,
			"remote_total":	0.868292586085121,
			"remote_user":	0.067791795513936562,
			"remote_system":	0.80050412153597983
		},
		"sender_tcp_congestion":	"cubic",
		"receiver_tcp_congestion":	"cubic"
	},
	"server_output_text":	"-----------------------------------------------------------\nServer listening on 5201 (test #155)\n-----------------------------------------------------------\nAccepted connection from 192.168.1.243, port 40320\n[  5] local 192.168.1.165 port 5201 connected to 192.168.1.243 port 40336\n[ ID] Interval           Transfer     Bitrate\n[  5]   0.00-1.00   sec  2.25 MBytes  18.9 Mbits/sec                  \n[  5]   1.00-2.00   sec  2.12 MBytes  17.8 Mbits/sec                  \n[  5]   2.00-3.00   sec  2.38 MBytes  19.9 Mbits/sec                  \n[  5]   3.00-4.00   sec  2.25 MBytes  18.9 Mbits/sec                  \n[  5]   4.00-5.00   sec  2.25 MBytes  18.9 Mbits/sec                  \n[  5]   5.00-6.00   sec  2.25 MBytes  18.9 Mbits/sec                  \n[  5]   6.00-7.00   sec  2.25 MBytes  18.9 Mbits/sec                  \n[  5]   7.00-8.00   sec  2.38 MBytes  19.9 Mbits/sec                  \n[  5]   8.00-9.00   sec  2.25 MBytes  18.9 Mbits/sec                  \n[  5]   9.00-10.00  sec  2.25 MBytes  18.9 Mbits/sec                  \n[  5]  10.00-11.00  sec  2.25 MBytes  18.9 Mbits/sec                  \n[  5]  11.00-12.00  sec  2.25 MBytes  18.9 Mbits/sec                  \n[  5]  12.00-13.00  sec  2.38 MBytes  19.9 Mbits/sec                  \n[  5]  13.00-14.00  sec  2.25 MBytes  18.9 Mbits/sec                  \n[  5]  14.00-15.00  sec  2.25 MBytes  18.9 Mbits/sec                  \n[  5]  15.00-16.00  sec  2.25 MBytes  18.9 Mbits/sec                  \n[  5]  16.00-17.00  sec  2.25 MBytes  18.9 Mbits/sec                  \n[  5]  17.00-18.00  sec  2.38 MBytes  19.9 Mbits/sec                  \n[  5]  18.00-19.00  sec  2.25 MBytes  18.9 Mbits/sec                  \n[  5]  19.00-20.00  sec  2.25 MBytes  18.9 Mbits/sec                  \n[  5]  20.00-21.00  sec  2.25 MBytes  18.9 Mbits/sec                  \n[  5]  21.00-22.00  sec  2.25 MBytes  18.9 Mbits/sec                  \n[  5]  22.00-23.00  sec  2.38 MBytes  19.9 Mbits/sec                  \n[  5]  23.00-24.00  sec  2.25 MBytes  18.9 Mbits/sec                  \n[  5]  24.00-25.00  sec  2.25 MBytes  18.9 Mbits/sec                  \n[  5]  25.00-26.00  sec  2.25 MBytes  18.9 Mbits/sec                  \n[  5]  26.00-27.00  sec  2.38 MBytes  19.9 Mbits/sec                  \n[  5]  27.00-28.00  sec  2.25 MBytes  18.9 Mbits/sec                  \n[  5]  28.00-29.00  sec  2.25 MBytes  18.9 Mbits/sec                  \n[  5]  29.00-30.00  sec  2.25 MBytes  18.9 Mbits/sec                  \n[  5]  30.00-30.02  sec   128 KBytes  51.7 Mbits/sec                  \n- - - - - - - - - - - - - - - - - - - - - - - - -\n[ ID] Interval           Transfer     Bitrate\n[  5]   0.00-30.02  sec  68.2 MBytes  19.1 Mbits/sec                  receiver\n"
}
