{
  "timestamp": "2025-11-27T17:43:52+05:00",
  "kernel": "/home/rakhat/ghq/github.com/4ry1337/TCP-AAD-Tests/results/tcpaad/metadata/rate34_bw50_delay50_iter2.json",
  "server_kernel_version": "6.12.9-gb9f85fb59f1f",
  "wifi_stats": {
    "rc_stats": "34",
    "station_info": "Station 50:c2:e8:e9:cf:ef (on wlan0) 	inactive time:	2930 ms 	rx bytes:	48761060 	rx packets:	472858 	tx bytes:	1323228513 	tx packets:	861220 	tx retries:	24136 	tx failed:	0 	signal:  	-21 [-29, -22] dBm 	signal avg:	-21 [-29, -21] dBm 	tx bitrate:	130.0 MBit/s MCS 15 	rx bitrate:	6.0 MBit/s 	expected throughput:	45.226Mbps 	authorized:	yes 	authenticated:	yes 	preamble:	short 	WMM/WME:	yes 	MFP:		no 	TDLS peer:	no 	connected time:	1131 seconds "
  },
  "tcp_stats": {
    "ss_output": "State Recv-Q Send-Q Local Address:Port Peer Address:Port "
  }
}
